cjm_fasthtml_interactions/__init__.py
cjm_fasthtml_interactions/_modidx.py
cjm_fasthtml_interactions/core/__init__.py
cjm_fasthtml_interactions/core/context.py
cjm_fasthtml_interactions/core/html_ids.py
cjm_fasthtml_interactions/core/state_store.py
cjm_fasthtml_interactions/patterns/__init__.py
cjm_fasthtml_interactions/patterns/async_loading.py
cjm_fasthtml_interactions/patterns/master_detail.py
cjm_fasthtml_interactions/patterns/modal_dialog.py
cjm_fasthtml_interactions/patterns/pagination.py
cjm_fasthtml_interactions/patterns/sse_connection_monitor.py
cjm_fasthtml_interactions/patterns/step_flow.py
cjm_fasthtml_interactions/patterns/tabbed_interface.py
cjm_fasthtml_interactions-0.0.24.dist-info/licenses/LICENSE
demo/__init__.py
demo/async_loading_demo.py
demo/home.py
demo/master_detail_demo.py
demo/modal_dialog_demo.py
demo/pagination_demo.py
demo/sse_monitor_demo.py
demo/step_flow_demo.py
demo/tabbed_interface_demo.py
cjm_fasthtml_interactions-0.0.24.dist-info/METADATA
cjm_fasthtml_interactions-0.0.24.dist-info/WHEEL
cjm_fasthtml_interactions-0.0.24.dist-info/entry_points.txt
cjm_fasthtml_interactions-0.0.24.dist-info/top_level.txt
cjm_fasthtml_interactions-0.0.24.dist-info/RECORD
