Metadata-Version: 2.4
Name: cjm-fasthtml-interactions
Version: 0.0.24
Summary: Reusable user interaction patterns for FastHTML applications including multi-step wizards, master-detail views, modal workflows, and other stateful UI orchestration patterns.
Home-page: https://github.com/cj-mills/cjm-fasthtml-interactions
Author: Christian J. Mills
Author-email: 9126128+cj-mills@users.noreply.github.com
License: Apache Software License 2.0
Keywords: nbdev jupyter notebook python
Classifier: Development Status :: 4 - Beta
Classifier: Intended Audience :: Developers
Classifier: Natural Language :: English
Classifier: Programming Language :: Python :: 3.11
Classifier: Programming Language :: Python :: 3.12
Classifier: License :: OSI Approved :: Apache Software License
Requires-Python: >=3.11
License-File: LICENSE
Requires-Dist: fastcore
Requires-Dist: cjm_error_handling
Requires-Dist: cjm_fasthtml_app_core
Requires-Dist: cjm_fasthtml_daisyui
Requires-Dist: cjm_fasthtml_sse
Provides-Extra: dev
Dynamic: author
Dynamic: author-email
Dynamic: classifier
Dynamic: description
Dynamic: description-content-type
Dynamic: home-page
Dynamic: keywords
Dynamic: license
Dynamic: license-file
Dynamic: provides-extra
Dynamic: requires-dist
Dynamic: requires-python
Dynamic: summary
